{
  "type": "create:sequenced_assembly",
  "ingredient": {
    "item": "kubejs:graphics_card_t1"
  },
  "transitionalItem": {
    "item": "kubejs:incomplete_graphics_card"
  },
  "sequence": [
    {
      "type": "create:filling",
      "ingredients": [
        {
          "item": "kubejs:incomplete_graphics_card"
        },
        {
          "fluid": "mekanismgenerators:fusion_fuel",
          
          "amount": 560
        }
      ],
      "results": [
        {
          "item": "kubejs:incomplete_graphics_card"
        }
      ]
    },
    {
      "type": "create:deploying",
      "ingredients": [
        {
          "item": "kubejs:incomplete_graphics_card"
        },
        {
          "item": "ae2:engineering_processor"
        }
      ],
      "results": [
        {
          "item": "kubejs:incomplete_graphics_card"
        }
      ]
    },
    {
      "type": "create:deploying",
      "ingredients": [
        {
          "item": "kubejs:incomplete_graphics_card"
        },
        {
          "item": "mekanism:pellet_polonium"
        }
      ],
      "results": [
        {
          "item": "kubejs:incomplete_graphics_card"
        }
      ]
    }
    
  ],
  "results": [
    {
      "item": "kubejs:graphics_card_t2",
      "chance": 1
    }
  ],
  "loops": 1
}